T5Custom/__init__.py
T5Custom/api.py
T5Custom/config.py
T5Custom/controller.py
T5Custom/custom_t5_model.py
T5Custom/experiment.py
T5Custom/load_model.py
T5Custom/main.py
T5Custom/operator_enum.py
T5Custom/run.py
T5Custom/test.py
T5Custom/training_data_creation.py
T5Custom/training_data_creation_new.py
T5Custom/util.py
T5Custom-1.1.0.dist-info/METADATA
T5Custom-1.1.0.dist-info/WHEEL
T5Custom-1.1.0.dist-info/top_level.txt
T5Custom-1.1.0.dist-info/RECORD
